LICENSE
nb2chan/__init__.py
nb2chan/config.py
nb2chan/mecho.py
nb2chan/nb2chan.py
nb2chan-0.1.1.dist-info/LICENSE
nb2chan-0.1.1.dist-info/WHEEL
nb2chan-0.1.1.dist-info/METADATA
nb2chan-0.1.1.dist-info/RECORD
