Metadata-Version: 2.1
Name: nb2chan
Version: 0.1.1
Summary: nb2chan push service Nonebot2酱推送
Home-page: https://github.com/ffreemt/nb2chan
License: MIT
Author: ffreemt
Requires-Python: >=3.7.3,<4.0
Classifier: License :: OSI Approved :: MIT License
Classifier: Programming Language :: Python :: 3
Classifier: Programming Language :: Python :: 3.10
Classifier: Programming Language :: Python :: 3.8
Classifier: Programming Language :: Python :: 3.9
Requires-Dist: aiocqhttp (>=1.4.2,<2.0.0)
Requires-Dist: logzero (>=1.7.0,<2.0.0)
Requires-Dist: nonebot-adapter-onebot (>=2.0.0-beta.1,<3.0.0)
Requires-Dist: nonebot2 (>=2.0.0-alpha.16,<3.0.0)
Requires-Dist: pendulum (>=2.1.2,<3.0.0)
Project-URL: Repository, https://github.com/ffreemt/nb2chan
